manipulation/__init__.py
manipulation/clutter.py
manipulation/conf.py
manipulation/create_sdf_from_mesh.md
manipulation/create_sdf_from_mesh.py
manipulation/directives_tree.py
manipulation/drake_gym.py
manipulation/envs/box_flipup.py
manipulation/envs/planar_gripper_pushing_a_box.py
manipulation/exercises/clutter/normal_solution.npy
manipulation/exercises/clutter/test_analytic_grasp.py
manipulation/exercises/clutter/test_grasp_candidate.py
manipulation/exercises/clutter/test_grasp_letters.py
manipulation/exercises/clutter/test_normal.py
manipulation/exercises/deep_perception/test_contrastive.py
manipulation/exercises/force/test_hybrid.py
manipulation/exercises/grader.py
manipulation/exercises/intro/test_hardwarestation_and_scenarios.py
manipulation/exercises/intro/test_intro_fundamentals.py
manipulation/exercises/intro/test_physics_simulation_and_robots.py
manipulation/exercises/mobile/test_mobile_base_ik.py
manipulation/exercises/pick/plot_planar_manipulator.py
manipulation/exercises/pick/test_differential_ik.py
manipulation/exercises/pick/test_pickplace_initials.py
manipulation/exercises/pick/test_planar_manipulator.py
manipulation/exercises/pick/test_rigid_transforms.py
manipulation/exercises/pick/test_robot_painter.py
manipulation/exercises/pick/test_simple_qp.py
manipulation/exercises/pose/test_icp.py
manipulation/exercises/pose/test_pickplace_initials_with_geometry.py
manipulation/exercises/pose/test_pose_estimation.py
manipulation/exercises/pose/test_ransac.py
manipulation/exercises/rl/test_stochastic_optimization.py
manipulation/exercises/rl/test_vpg.py
manipulation/exercises/robot/test_direct_joint_control.py
manipulation/exercises/robot/test_hardware_station_io.py
manipulation/exercises/robot/test_pid.py
manipulation/exercises/robot/test_reflected_inertia.py
manipulation/exercises/robot/test_survey.py
manipulation/exercises/segmentation/test_mask.py
manipulation/exercises/segmentation/test_segmentation_and_grasp.py
manipulation-2025.10.19.dist-info/LICENSE.TXT
manipulation-2025.10.19.dist-info/METADATA
manipulation-2025.10.19.dist-info/WHEEL
manipulation-2025.10.19.dist-info/RECORD
